android_notify/__init__.py
android_notify/__main__.py
android_notify/base.py
android_notify/config.py
android_notify/core.py
android_notify/styles.py
android_notify/sword.py
android_notify/fallback-icons/flet-appicon.png
android_notify/fallback-icons/pydroid3-appicon.png
android_notify/internal/an_types.py
android_notify/internal/android.py
android_notify/internal/channels.py
android_notify/internal/facade.py
android_notify/internal/helper.py
android_notify/internal/intents.py
android_notify/internal/java_classes.py
android_notify/internal/logger.py
android_notify/internal/permissions.py
android_notify/tests/__init__.py
android_notify/tests/android_notify_test.py
android_notify/tests/base_test.py
android_notify/tests/main.py
android_notify/tests/test_basic_notifications.py
android_notify/tests/test_notification_actions.py
android_notify/tests/test_notification_appearance.py
android_notify/tests/test_notification_behavior.py
android_notify/tests/test_notification_channels.py
android_notify/tests/test_notification_clear.py
android_notify/tests/test_notification_permission.py
android_notify/tests/test_notification_progress.py
android_notify/tests/test_notification_sound.py
android_notify/tests/test_notification_styles.py
android_notify/tests/flet/adv/main.py
android_notify/tests/flet/adv/tests/__init__.py
android_notify/tests/flet/adv/tests/test_android_notify_full.py
android_notify/tests/flet/basic/src/main.py
android_notify/tests/flet/flet-working/src/main.py
android_notify/tests/p4a/hook.py
android_notify/tests/serivces/wallpaper.py
android_notify/widgets/images.py
android_notify/widgets/texts.py
docs/website/src/pages/data/laner_Sent.py
android_notify-1.60.8.dist-info/METADATA
android_notify-1.60.8.dist-info/WHEEL
android_notify-1.60.8.dist-info/entry_points.txt
android_notify-1.60.8.dist-info/top_level.txt
android_notify-1.60.8.dist-info/RECORD
