Metadata-Version: 2.4
Name: android-notify
Version: 1.60.8
Summary: A Python package that simplifies creating Android notifications in Kivy and Flet apps.
Author-email: Fabian <fector101@yahoo.com>
License-Expression: MIT
Project-URL: Homepage, https://android-notify.vercel.app
Project-URL: Documentation, https://android-notify.vercel.app/
Project-URL: Source, https://github.com/fector101/android_notify
Project-URL: Tracker, https://github.com/fector101/android_notify/issues
Project-URL: Funding, https://www.buymeacoffee.com/fector101
Keywords: android,notifications,kivy,mobile,post-notifications,pyjnius,android-notifications,kivy-notifications,python-android,mobile-development,push-notifications,mobile-app,kivy-application
Classifier: Programming Language :: Python :: 3
Classifier: Operating System :: Android
Classifier: Development Status :: 5 - Production/Stable
Classifier: Intended Audience :: Developers
Classifier: Topic :: Software Development :: Libraries :: Python Modules
Requires-Python: >=3.6
Requires-Dist: pyjnius>=1.4.2
Provides-Extra: dev
Requires-Dist: kivy>=2.0.0; extra == "dev"
